LICENSE
MANIFEST.in
README.rst
setup.py
asyncdef.emitter.egg-info/PKG-INFO
asyncdef.emitter.egg-info/SOURCES.txt
asyncdef.emitter.egg-info/dependency_links.txt
asyncdef.emitter.egg-info/entry_points.txt
asyncdef.emitter.egg-info/not-zip-safe
asyncdef.emitter.egg-info/requires.txt
asyncdef.emitter.egg-info/top_level.txt
asyncdef/emitter/__init__.py
asyncdef/emitter/emitter.py
asyncdef/emitter/test_emitter.py