Metadata-Version: 1.0
Name: asyncdef.emitter
Version: 0.1.1
Summary: Tools for handling async events.
Home-page: https://github.com/asyncdef/emitter
Author: Kevin Conway
Author-email: kevinjacobconway@gmail.com
License: Apache 2.0
Platform: UNKNOWN
